pyutilkit/__init__.py
pyutilkit/file_utils/__init__.py
pyutilkit/file_utils/io.py
pyutilkit/file_utils/management.py
pyutilkit/file_utils/metadata.py
pyutilkit/list_utils/__init__.py
pyutilkit/list_utils/analysis.py
pyutilkit/list_utils/manipulation.py
pyutilkit/list_utils/transformation.py
pyutilkit/math_utils/__init__.py
pyutilkit/math_utils/arithmetic.py
pyutilkit/math_utils/number_theory.py
pyutilkit/math_utils/statistics.py
pyutilkit/string_utils/__init__.py
pyutilkit/string_utils/case_conversion.py
pyutilkit/string_utils/manipulation.py
pyutilkit/string_utils/validation.py
pyutilkit_sarvs-0.1.0.dist-info/licenses/LICENSE
tests/__init__.py
tests/test_main.py
pyutilkit_sarvs-0.1.0.dist-info/METADATA
pyutilkit_sarvs-0.1.0.dist-info/WHEEL
pyutilkit_sarvs-0.1.0.dist-info/top_level.txt
pyutilkit_sarvs-0.1.0.dist-info/RECORD
