Metadata-Version: 2.4
Name: pyutilkit-sarvs
Version: 0.1.0
Summary: A multi-purpose Python utility toolkit
Home-page: https://github.com/Sarvesh-Kannan/PyUtilKit
Author: Sarvesh Kannan
Author-email: your.email@example.com
Project-URL: Bug Reports, https://github.com/Sarvesh-Kannan/PyUtilKit/issues
Project-URL: Source, https://github.com/Sarvesh-Kannan/PyUtilKit
Keywords: utility,helper,tools,string manipulation,file handling,mathematics
Classifier: Development Status :: 3 - Alpha
Classifier: Intended Audience :: Developers
Classifier: License :: OSI Approved :: MIT License
Classifier: Programming Language :: Python :: 3
Classifier: Programming Language :: Python :: 3.7
Classifier: Programming Language :: Python :: 3.8
Classifier: Programming Language :: Python :: 3.9
Classifier: Programming Language :: Python :: 3.10
Classifier: Programming Language :: Python :: 3.11
Classifier: Topic :: Software Development :: Libraries :: Python Modules
Requires-Python: >=3.7
License-File: LICENSE
Dynamic: author
Dynamic: author-email
Dynamic: classifier
Dynamic: description
Dynamic: description-content-type
Dynamic: home-page
Dynamic: keywords
Dynamic: license-file
Dynamic: project-url
Dynamic: requires-python
Dynamic: summary
